{
  "id": "dox_1771375277351_0a8487131e3c",
  "nick": "Gaweł",
  "shortDesc": "He thinks he is the god of everything",
  "fullDesc": "Name: Maksymilian\nSurname: Gawlas\nAge: 19\nBirthday: 27.03.2006\nPhone Number: 507 938 068 \nPesel: 06232700655\nMail: gawlasmaksymilian@gmail.com\nIP: 37.31.24.3\nCity: Siewierz\nFamily City: Siemanowice Slaskie\nOperator: T-Mobile\nBank: ING\n \nDiscord Nick: gawlowski_\nDiscord ID: 841772569316818995\n\nDad Name: Łukasz\nDad Surname: Gawlas\n\nBrother Name: Marcel\nBrother Surname: Gawlas\n\nSister Name: Martyna\nSister Surname: Gawlas",
  "tables": [
    {
      "title": "Links",
      "data": {
        "Facebook": "https://www.facebook.com/JestemMaksiu123",
        "Instagram": "https://www.instagram.com/witajztejstronymaksiu?igsh=MXZkemtsdHJ4amNmeA==",
        "TikTok": "https://www.tiktok.com/@gawcio_edit?_t=ZN-8zBexlX364k&_r=1"
      }
    }
  ],
  "images": [],
  "createdAt": "2026-02-18T00:41:17.352Z",
  "ipHash": "261f4c01c2bdca4073e8e46e965ebe2ba631f70b4ce0dddfc285f59f499c6e34"
}